Workbook
Name Account: COA_List
Name Customer_List: Customers!$A$1:$C$5
Name Customer_Name: Customers_List
Name SKU: SKU_List
Name Supplier_Name: Supplier_List

Sheet Dashboard
A1: PT Nusantara Office Supplies | K1: Project Information
A2: Accounting Management Dashboard | K2: Company | L2: PT Nusantara Office Supplies
A3: Period: January 2026 | K3: Period | L3: 46023
K4: Accounting Basis | L4: Accrual Basis
A5: Sales | C5: Cash | E5: Inventory | G5: Profit | K5: Currency | L5: Indonesian Rupiah (IDR)
K6: Software | L6: Microsoft Excel
A8: 3560000 | C8: 66460000 | E8: 36400000 | G8: -3840000
A24: Financial Summary
A25: Total Asset | E25: ='Balance Sheet'!G16 -> 121660000
A26: Total Liabilities | E26: ='Balance Sheet'!G22 -> 5500000
A27: Total Equity | E27: ='Balance Sheet'!G28 -> 116160000
A29: Prepared By
A30: Sri Wahyuni
A31: Accounting Portfolio
A32: Microsoft Excel
A58: Recent Transaction
A59: Date | B59: Ref | C59: Description | D59: Amount
A60: 46034 | B60: INV2501003 | C60: Cash Sales | D60: 210000
A61: 46033 | B61: PAYROLL2501001 | C61: Salary | D61: 5500000
A62: 46032 | B62: FA2501001 | C62: Printer | D62: 3800000
A63: 46031 | B63: RCPT2501002 | C63: Receive Payment | D63: 3000000
A64: 46030 | B64: PAY2501003 | C64: Internet | D64: 650000

Sheet Read Me
A1: Accounting Management System
A2: Prepared by
A3: Sri Wahyuni
A5: Objective
A6: This project demonstrates a complete accounting cycle using Microsoft Excel.
A8: Features
A9: ✅ Chart of Accounts
A10: ✅ Opening Balance
A11: ✅ Customers
A12: ✅ Suppliers
A13: ✅ Inventory
A14: ✅ Sales
... A27: Excel Skills Used
A28: - | B28: SUMIFS
A29: - | B29: VLOOKUP
A30: - | B30: Data Validation
A31: - | B31: Conditional Formatting
A32: - | B32: Charts
A33: - | B33: Financial Reporting

Sheet Dashboard_data
A3: A | B3: B | D3: Category | E3: Amount
A4: Total Sales | B4: =SUMIFS('General Journal'!E5:E28,'General Journal'!C5:C28,"Sales Revenue") -> 3560000 | D4: Sales | E4: 3560000
A5: Cash | B5: ='Balance Sheet'!G6 -> 66460000 | D5: Expenses | E5: 7400000
A6: Inventory | B6: ='Balance Sheet'!G8 -> 36400000
A7: Net Loss | B7: ='Income Statement'!G20 -> -3840000
A12: Asset | B12: Amount
A13: Cash | B13: 66460000
A14: Inventory | B14: 36400000
A15: Office Equipment | B15: 18800000

Sheet Opening Balance
A1: Date | B1: Account Code | C1: Account Name | D1: Debit | E1: Credit
A2: 46023 | B2: 1010 | C2: Cash | D2: 75000000
A3: 46023 | B3: 1040 | C3: Inventory | D3: 30000000
A4: 46023 | B4: 1510 | C4: Office Equipment | D4: 15000000
A5: 46023 | B5: 3010 | C5: Owner's Capital | E5: 120000000

Sheet COA
A1: Code | B1: Account
A2: 1010 | B2: Cash
A3: 102 | B3: Bank
A4: 103 | B4: Accounts Receivable
A5: 1040 | B5: Inventory
A6: 1510 | B6: Office Euipment
A7: 201 | B7: Accounts Payable
A8: 3010 | B8: Capital
A9: 401 | B9: Sales
A10: 4010 | B10: Sales Return
A11: 501 | B11: Salary Expense
A12: 5010 | B12: Rent Expense
A13: 5020 | B13: Electricity Expense

Sheet Customers
A1: Customer ID | B1: Customer Name | C1: Phone
A2: CUS001 | B2: PT Maju Bersama | C2: 0812xxxxx
A3: CUS002 | B3: CV Sentosa | C3: 0857xxxx
A4: CUS003 | B4: PT Sejahtera | C4: 0888xxx
A5: CUS004 | B5: CV Prima Stationery | C5: 087xxxx

Sheet Suppliers
A1: Supplier ID | B1: Supplier Name | C1: Phone
A2: SUP001 | B2: PT Sumber Jaya | C2: 021-2xxxx
A3: SUP002 | B3: PT Kertas Indonesia | C3: 021-5xxx
A4: SUP003 | B4: PT Pena Nusantara | C4: 021-9xxxx

Sheet Inventory
A1: SKU | B1: Item | C1: Cost | D1: Selling Price | E1: Stock
A2: P001 | B2: A4 Paper | C2: 55000 | D2: 75000 | E2: 100
A3: P002 | B3: Ballpoint Pen | C3: 4500 | D3: 7000 | E3: 250
A4: P003 | B4: Stepler | C4: 25000 | D4: 38000 | E4: 40
A5: P004 | B5: Notebook A5 | C5: 12000 | D5: 18000 | E5: 120
A6: P005 | B6: Whiteboard Marker | C6: 8000 | D6: 12000 | E6: 80

Sheet Sales
A1: Sales
A2: PT Nusantara Office Supplies
A4: Invoice | B4: Date | C4: Customer | D4: Payment Type | E4: SKU | F4: Item | G4: Qty | H4: Price | I4: Total
A5: INV2601001 | B5: 46027 | C5: PT Maju Bersama | D5: Credit | E5: P001 | F5: =VLOOKUP(E5,Inventory!A1:B6,2,FALSE) -> A4 Paper | G5: 40 | H5: =VLOOKUP(E5,Inventory!A1:D6,4,0) -> 75000 | I5: =G5*H5 -> 3000000
A6: INV2601002 | B6: 46028 | C6: Walk-In Customer | D6: Cash | E6: P002 | F6: =VLOOKUP(E6,Inventory!A2:B7,2,FALSE) -> Ballpoint Pen | G6: 50 | H6: =VLOOKUP(E6,Inventory!A2:D7,4,0) -> 7000 | I6: =G6*H6 -> 350000
A7: INV2601003 | B7: 46034 | C7: Walk-In Customer | D7: Cash | E7: P002 | F7: =VLOOKUP(E7,Inventory!A3:B8,2,FALSE) -> Ballpoint Pen | G7: 30 | H7: =VLOOKUP(E7,Inventory!A3:D8,4,0) -> 7000 | I7: =G7*H7 -> 210000

Sheet Purchases
A1: Purchase
A2: PT Nusantara Office Supplies
A4: PO | B4: Date | C4: Supplier | D4: Payment Type | E4: SKU | F4: Item | G4: Qty | H4: Cost | I4: Total
A5: PO2601001 | B5: 46025 | C5: PT Kertas Indonesia | D5: Credit | E5: P001 | F5: =VLOOKUP(E5,Inventory!A1:B6,2,0) -> A4 Paper | G5: 100 | H5: =VLOOKUP(E5,Inventory!A1:C6,3,0) -> 55000 | I5: =H5*G5 -> 5500000
A6: PO2601002 | B6: 46026 | C6: PT Pena Nusantara | D6: Cash | E6: P002 | F6: =VLOOKUP(E6,Inventory!A2:B7,2,0) -> Ballpoint Pen | G6: 200 | H6: =VLOOKUP(E6,Inventory!A2:C7,3,0) -> 4500 | I6: =H6*G6 -> 900000

Sheet Cash Receipt
A1: Cash Receipt
A2: PT Nusantara Office Supplies
A4: Receipt No. | B4: Date | C4: Reference | D4: Customer | E4: Reference Invoice | F4: Payment Method | G4: Amount
A5: RCPT2601001 | B5: 46028 | C5: INV2601002 | D5: Walk-In Customer | E5: INV2601002 | F5: Cash | G5: 350000
A6: RCPT2601002 | B6: 46031 | C6: INV2601001 | D6: PT Maju Bersama | E6: INV2601001 | F6: Bank Transfer | G6: 3000000
A7: RCPT2601003 | B7: 46034 | C7: INV2601003 | D7: Walk-In Customer | E7: INV2601003 | F7: Cash | G7: 710000

Sheet Cash Payment
A1: Cash Payment
A2: PT Nusantara Office Supplies
A4: Payment No. | B4: Date | C4: Payee | D4: Reference | E4: Description | F4: Payment Method | G4: Amount
A5: PAY2601001 | B5: 46026 | C5: PT Pena Nusantara | D5: PO2601002 | E5: Ballpoint Pen | F5: Cash | G5: 900000
A6: PAY2601002 | B6: 46029 | C6: PLN | D6: EXP2601001 | E6: Electricity Expense | F6: Bank Transfer | G6: 1250000
A7: PAY2601003 | B7: 46030 | C7: Internet Provider | D7: EXP2601002 | E7: Intenet Expense | F7: Bank Transfer | G7: 650000
A8: PAY2601004 | B8: 46032 | C8: PT Office Equipment | D8: FA2601001 | E8: Fixed Asset Purchase | F8: Bank Transfer | G8: 3800000
A9: PAY2601005 | B9: 46033 | C9: Employes | D9: PAYROLL2601001 | E9: Salary Expense | F9: Bank Transfer | G9: 5500000

Sheet General Journal
A1: General Journal
A2: PT Nusantara Office Supplies
A3: Periode: Jan 1 - Jan 12, 2026
A4: Date | B4: Reference | C4: Account | D4: Debit | E4: Credit | F4: Description
A5: 46023 | B5: OB2026001 | C5: Cash | D5: 75000000
B6: OB2026001 | C6: Inventory | D6: 30000000
B7: OB2026001 | C7: Office Equipment | D7: 15000000
B8: OB2026001 | C8: Owner's Capital | E8: 120000000
A9: 46025 | B9: PO2601001 | C9: Inventory | D9: 5500000 | F9: Purchases PT Kertas Indonesia
C10: Account Payable | E10: 5500000
A11: 46026 | B11: PO2601002 | C11: Inventory | D11: 900000 | F11: Purchases PT Pena Nusantara
C12: cash | E12: 900000
A13: 46027 | B13: INV2601001 | C13: Account Receivable | D13: 3000000 | F13: Sales from PT Maju Bersama
C14: Sales Revenue | E14: 3000000
A15: 46028 | B15: INV2601002 | C15: Cash | D15: 350000 | F15: Sales
C16: Sales Revenue | E16: 350000
A17: 46029 | B17: PAY2601002 | C17: Electricity Expense | D17: 1250000 | F17: Electricity Expense
C18: cash | E18: 1250000
A19: 46030 | B19: PAY2601003 | C19: Internet Expense | D19: 650000 | F19: Internet Expense
C20: cash | E20: 650000
A21: 46031 | B21: RCPT2601002 | C21: cash | D21: 3000000 | F21: Payment from PT Maju Bersama
C22: Account Receivable | E22: 3000000
A23: 46032 | B23: FA2601001 | C23: Office Equipment | D23: 3800000 | F23: Buy Printer
C24: Cash | E24: 3800000
A25: 46033 | B25: PAYROLL2601001 | C25: Salary Expense | D25: 5500000 | F25: Salary Expense
C26: Cash | E26: 5500000
A27: 46034 | B27: INV2601003 | C27: Cash | D27: 210000 | F27: Sales
C28: Sales Revenue | E28: 210000

Sheet General Ledger
A1: General Ledger
A2: PT Nusantara Office Supplies
A3: Periode: Jan 1 - Jan 12, 2026
A4: Date | B4: Reference | C4: Account | D4: Description | E4: Debit | F4: Credit | G4: Balance
A5: 46023 | B5: OB2026001 | C5: Cash | D5: Opening Balance | E5: 75000000 | G5: =E5 -> 75000000
A6: 46026 | B6: PO2601002 | C6: Cash | D6: Purchase Inventory | F6: 900000 | G6: =G5-F6 -> 74100000
A7: 46028 | B7: INV2601002 | C7: Cash | D7: Cash Sales | E7: 350000 | G7: =G6+E7 -> 74450000
A8: 46029 | B8: PAY2601002 | C8: Cash | D8: Electricity Bill | F8: 1250000 | G8: =G7-F8 -> 73200000
A9: 46030 | B9: PAY2601003 | C9: Cash | D9: Internet Bill | F9: 650000 | G9: =G8-F9 -> 72550000
A10: 46031 | B10: RCPT2601002 | C10: Cash | D10: Collection of A/R | E10: 3000000 | G10: =G9+E10 -> 75550000
A11: 46032 | B11: FA2601001 | C11: Cash | D11: Purchase Printer | F11: 3800000 | G11: =G10-F11 -> 71750000
A12: 46033 | B12: PAYROLL2601001 | C12: Cash | D12: Salary Payment | F12: 5500000 | G12: =G11-F12 -> 66250000
A13: 46034 | B13: INV2601003 | C13: Cash | D13: Cash Sales | E13: 210000 | G13: =G12+E13 -> 66460000
A14: 46023 | B14: OB2026001 | C14: Inventory | D14: Opening Balance | E14: 30000000 | G14: =E14 -> 30000000
A15: 46025 | B15: PO2601001 | C15: Inventory | D15: Purchase Inventory | E15: 5500000 | G15: =G14+E15 -> 35500000
A16: 46026 | B16: PO2601002 | C16: Inventory | D16: Purchase Inventory | E16: 900000 | G16: =G15+E16 -> 36400000
A17: 46023 | B17: OB2026001 | C17: Office Equipment | D17: Opening Balance | E17: 15000000 | G17: =E17 -> 15000000
A18: 46032 | B18: FA2601001 | C18: Office Equipment | D18: Purchase Printer | E18: 3800000 | G18: =G17+E18 -> 18800000
A19: 46027 | B19: INV2601001 | C19: Account Receivable | D19: Sales | E19: 3000000 | G19: =E19 -> 3000000
A20: 46031 | B20: RCPT2601002 | C20: Account Receivable | D20: Collection of A/R | F20: 3000000 | G20: =G19-F20 -> 0
A21: 46025 | B21: PO2601001 | C21: Account Payable | D21: Purchase Inventory | F21: 5500000 | G21: =F21 -> 5500000
A22: 46023 | B22: OB2026001 | C22: Owner's capital | D22: Opening Balance | F22: 120000000 | G22: =F22 -> 120000000
A23: 46027 | B23: INV2601001 | C23: Sales | D23: Sales | F23: 3000000 | G23: =F23 -> 3000000
A24: 46028 | B24: INV2601002 | C24: Sales | D24: Cash Sales | F24: 350000 | G24: =G23+F24 -> 3350000
A25: 46034 | B25: INV2601003 | C25: Sales | D25: Cash Sales | F25: 210000 | G25: =G24+F25 -> 3560000
A26: 46029 | B26: PAY2601002 | C26: Electricity Expense | D26: Electricity Bill | E26: 1250000 | G26: =E26 -> 1250000
A27: 46030 | B27: PAY2601003 | C27: Internet Expense | D27: Internet Bill | E27: 650000 | G27: =E27 -> 650000
A28: 46033 | B28: PAYROLL2601001 | C28: Salary Expense | D28: Salary January | E28: 5500000 | G28: =E28 -> 5500000

Sheet Trial Balance
A1: Trial Balance
A2: PT Nusantara Office Supplies
A3: As of 12 January 2026
A4: No. Account | C4: Account | E4: Debit | G4: Credit
A5: 1010 | C5: Cash | E5: 66460000
A6: 1030 | C6: Accounts Receivable | E6: -
A7: 1040 | C7: Inventory | E7: 36400000
A8: 1510 | C8: Office Equipment | E8: 18800000
A9: 2010 | C9: Accounts Payable | G9: 5500000
A10: 3010 | C10: Owner's Capital | G10: 120000000
A11: 4010 | C11: Sales Revenue | G11: 3560000
A12: 5020 | C12: Salary Expense | E12: 5500000
A13: 5040 | C13: Electricity Expense | E13: 1250000
A14: 5050 | C14: Internet Expense | E14: 650000
A15: Total | E15: =SUM(E5:E14) -> 129060000 | G15: =SUM(G5:G14) -> 129060000

Sheet Income Statement
A1: PT Nusantara Office Supplies
A2: Income Statement
A3: For the Period Ended 12 January 2026
B4: Revenue
B5: Sales Revenue | G5: Amount (Rp)
B6: Total Revenue | G6: 3560000
G7: =G6 -> 3560000
B8: Operating Expenses
B9: Expense
B10: Salary Expense | G10: Amount (Rp)
B11: Electricity Expense | G11: 5500000
B12: Internet Expense | G12: 1250000
B13: Total Operating Expenses | G13: 650000
G14: =SUM(G11:G13) -> 7400000
B15: Net Income (Loss)
B17: Total Revenue | G17: Amount (Rp)
B18: Less: Total Operating Expenses | G18: =G7 -> 3560000
B19: Net Loss | G19: =G7-G14 -> -3840000
G20: =G19 -> -3840000

Sheet Balance Sheet
A1: PT Nusantara Office Supplies
A2: Balance Sheet
A3: As of 12 January 2026
B4: Assets
B5: Current Assets | G5: Amount (Rp)
B6: Account | G6: 66460000
B7: Cash | G7: 0
B8: Accounts Receivable | G8: 36400000
B9: Inventory | G9: =SUM(G6:G8) -> 102860000
B10: Total Current Assets
B12: Non-Current Assets | G12: Amount (Rp)
B13: Account | G13: 18800000
B14: Office Equipment | G14: =G13 -> 18800000
B15: Total Non-Current Assets
G16: =G9+G14 -> 121660000
B17: Total Assets
B19: Liabilities
B20: Current Liabilities | G20: Amount (Rp)
B21: Account | G21: 5500000
B22: Accounts Payable | G22: =G21 -> 5500000
B23: Total Liabilities
B25: Equity | G25: Amount (Rp)
B26: Account | G26: 120000000
B27: Owner's Capital | G27: -3840000
B28: Current Period Net Loss | G28: =G26+G27 -> 116160000
B29: Total Equity
